portfolio_opt/__init__.py
portfolio_opt/main.py
portfolio_opt/portfolio_backtester.py
portfolio_opt/portfolio_plotter.py
portfolio_opt-0.1.0.dist-info/METADATA
portfolio_opt-0.1.0.dist-info/WHEEL
portfolio_opt-0.1.0.dist-info/entry_points.txt
portfolio_opt-0.1.0.dist-info/RECORD
