Metadata-Version: 2.3
Name: portfolio-opt
Version: 0.1.0
Summary: 
Author: ohmji
Author-email: 53232225+ohmji@users.noreply.github.com
Requires-Python: >=3.13,<4.0
Classifier: Programming Language :: Python :: 3
Classifier: Programming Language :: Python :: 3.13
Requires-Dist: cvxpy (>=1.6.5,<2.0.0)
Requires-Dist: matplotlib (>=3.10.3,<4.0.0)
Requires-Dist: mkdocs-material (>=9.6.14,<10.0.0)
Requires-Dist: mkdocs-mermaid2-plugin (>=1.2.1,<2.0.0)
Requires-Dist: mplfinance (>=0.12.10b0,<0.13.0)
Requires-Dist: numpy (>=2.2.5,<3.0.0)
Requires-Dist: pandas (>=2.2.3,<3.0.0)
Requires-Dist: pymdown-extensions (>=10.15,<11.0)
Requires-Dist: scipy (>=1.15.3,<2.0.0)
Requires-Dist: vectorbt (>=0.27.3,<0.28.0)
Requires-Dist: yfinance (>=0.2.61,<0.3.0)
